datadrift/__init__.py
datadrift/checker.py
data_drift-0.0.0.dist-info/METADATA
data_drift-0.0.0.dist-info/WHEEL
data_drift-0.0.0.dist-info/top_level.txt
data_drift-0.0.0.dist-info/RECORD
