Metadata-Version: 2.1
Name: data-drift
Version: 0.0.0
Summary: datadrift package
Home-page: UNKNOWN
License: MIT
Platform: UNKNOWN
Classifier: License :: OSI Approved :: MIT License
Classifier: Programming Language :: Python :: 3
Classifier: Programming Language :: Python :: 3.7
